mdns_generator/__init__.py
mdns_generator/cli.py
mdns_generator/config.py
mdns_generator/discovery.py
mdns_generator/generator.py
mdns_generator/logger.py
mdns_generator/platform_compat.py
mdns_generator/service.py
mdns_traffic_generator-1.0.0.dist-info/licenses/LICENSE
mdns_traffic_generator-1.0.0.dist-info/METADATA
mdns_traffic_generator-1.0.0.dist-info/WHEEL
mdns_traffic_generator-1.0.0.dist-info/entry_points.txt
mdns_traffic_generator-1.0.0.dist-info/top_level.txt
mdns_traffic_generator-1.0.0.dist-info/RECORD
