Metadata-Version: 2.4
Name: mdns-traffic-generator
Version: 1.0.0
Summary: A Python tool for generating mDNS traffic for network testing
Author: MDNS Generator Team
License-Expression: MIT
Project-URL: Homepage, https://github.com/example/mdns-traffic-generator
Project-URL: Documentation, https://github.com/example/mdns-traffic-generator#readme
Project-URL: Repository, https://github.com/example/mdns-traffic-generator
Project-URL: Issues, https://github.com/example/mdns-traffic-generator/issues
Keywords: mdns,multicast,dns,network,testing,zeroconf
Classifier: Development Status :: 4 - Beta
Classifier: Environment :: Console
Classifier: Intended Audience :: Developers
Classifier: Intended Audience :: System Administrators
Classifier: Operating System :: Microsoft :: Windows
Classifier: Operating System :: POSIX :: Linux
Classifier: Operating System :: MacOS
Classifier: Programming Language :: Python :: 3
Classifier: Programming Language :: Python :: 3.8
Classifier: Programming Language :: Python :: 3.9
Classifier: Programming Language :: Python :: 3.10
Classifier: Programming Language :: Python :: 3.11
Classifier: Programming Language :: Python :: 3.12
Classifier: Topic :: System :: Networking
Classifier: Topic :: Software Development :: Testing
Requires-Python: >=3.8
License-File: LICENSE
Requires-Dist: zeroconf>=0.131.0
Requires-Dist: click>=8.0.0
Provides-Extra: dev
Requires-Dist: pytest>=7.0.0; extra == "dev"
Requires-Dist: pytest-cov>=4.0.0; extra == "dev"
Requires-Dist: pytest-asyncio>=0.21.0; extra == "dev"
Requires-Dist: pylint>=3.0.0; extra == "dev"
Requires-Dist: black>=23.0.0; extra == "dev"
Requires-Dist: isort>=5.12.0; extra == "dev"
Requires-Dist: mypy>=1.0.0; extra == "dev"
Dynamic: license-file
